grnndata/GRNAnnData.py
grnndata/TF.txt
grnndata/VERSION
grnndata/__init__.py
grnndata/celltype.gmt
grnndata/mTF.txt
grnndata/utils.py
grnndata-1.1.5.dist-info/METADATA
grnndata-1.1.5.dist-info/WHEEL
grnndata-1.1.5.dist-info/entry_points.txt
grnndata-1.1.5.dist-info/licenses/LICENSE
grnndata-1.1.5.dist-info/RECORD
