Metadata-Version: 2.3
Name: grnndata
Version: 1.1.5
Summary: Awesome gene regulatory network enhanced anndata
Project-URL: repository, https://github.com/cantinilab/GRnnData
Author-email: jkobject <jkobject@gmail.com>
License: MIT
Keywords: anndata,gene regulatory networks,scPRINT,scRNAseq
Requires-Python: >=3.10
Requires-Dist: anndata>=0.8.0
Requires-Dist: d3graph>=0.2.0
Requires-Dist: gseapy>=1.0.0
Requires-Dist: leidenalg>=0.8.0
Requires-Dist: louvain>=0.8.0
Requires-Dist: natsort>=7.1.0
Requires-Dist: networkx>=2.6.0
Requires-Dist: numba>=0.56.0
Requires-Dist: numpy>=1.21.0
Requires-Dist: powerlaw>=1.5.0
Requires-Dist: pyvis>=0.1.9
Requires-Dist: scanpy>=1.10.0
Requires-Dist: scikit-learn>=1.0.0
Requires-Dist: scipy>=1.7.0
Requires-Dist: setuptools>=58.0.0
Provides-Extra: dev
Requires-Dist: coverage>=7.3.2; extra == 'dev'
Requires-Dist: gitchangelog>=3.0.4; extra == 'dev'
Requires-Dist: mkdocs-git-authors-plugin>=0.4.0; extra == 'dev'
Requires-Dist: mkdocs-git-revision-date-localized-plugin>=1.0.0; extra == 'dev'
Requires-Dist: mkdocs-jupyter>=0.2.0; extra == 'dev'
Requires-Dist: mkdocs>=1.5.3; extra == 'dev'
Requires-Dist: mkdocstrings-python>=0.10.0; extra == 'dev'
Requires-Dist: mkdocstrings>=0.22.0; extra == 'dev'
Requires-Dist: pytest-cov>=4.1.0; extra == 'dev'
Requires-Dist: pytest>=7.4.3; extra == 'dev'
Requires-Dist: ruff>=0.6.4; extra == 'dev'
